prey/__init__.py
prey/bin/__init__.py
prey-0.1.4.dist-info/entry_points.txt
prey-0.1.4.dist-info/LICENSE
prey-0.1.4.dist-info/WHEEL
prey-0.1.4.dist-info/METADATA
prey-0.1.4.dist-info/RECORD
