Metadata-Version: 2.1
Name: prey
Version: 0.1.4
Summary: A tool for writing shell scripts in python.
Home-page: https://github.com/sachinraja/prey
License: MIT
Author: Sachin Raja
Author-email: sachinraja2349@gmail.com
Requires-Python: >=3.7
Classifier: License :: OSI Approved :: MIT License
Classifier: Programming Language :: Python :: 3
Classifier: Programming Language :: Python :: 3.7
Classifier: Programming Language :: Python :: 3.8
Classifier: Programming Language :: Python :: 3.9
Requires-Dist: aiohttp (>=3.7.4,<4.0.0)
Requires-Dist: aiohttp-requests (>=0.1.3,<0.2.0)
Requires-Dist: colorama (>=0.4.4,<0.5.0)
Project-URL: Repository, https://github.com/sachinraja/prey
